omfpandas/__init__.py
omfpandas/audit.py
omfpandas/base.py
omfpandas/blockmodel.py
omfpandas/blockmodels/__init__.py
omfpandas/blockmodels/attributes.py
omfpandas/blockmodels/convert_blockmodel.py
omfpandas/blockmodels/coordinate_encoding.py
omfpandas/blockmodels/geometry.py
omfpandas/extras.py
omfpandas/reader.py
omfpandas/utils/__init__.py
omfpandas/utils/pandas_utils.py
omfpandas/utils/pandera_utils.py
omfpandas/utils/timer_utils.py
omfpandas/writer.py
omfpandas-0.9.2.dist-info/LICENSE
omfpandas-0.9.2.dist-info/METADATA
omfpandas-0.9.2.dist-info/WHEEL
omfpandas-0.9.2.dist-info/entry_points.txt
omfpandas-0.9.2.dist-info/RECORD
