Metadata-Version: 2.1
Name: omfpandas
Version: 0.9.2
Summary: A package for reading and writing OMF data with pandas
Home-page: https://github.com/elphick/omfpandas
Author: Greg
Author-email: 11791585+elphick@users.noreply.github.com
Requires-Python: >=3.9,<3.13
Classifier: Programming Language :: Python :: 3
Classifier: Programming Language :: Python :: 3.9
Classifier: Programming Language :: Python :: 3.10
Classifier: Programming Language :: Python :: 3.11
Provides-Extra: profile
Provides-Extra: validate
Requires-Dist: omf (>=2.0.0a0)
Requires-Dist: omfvista (>=0.3.0,<0.4.0)
Requires-Dist: pandas (>=2.0)
Requires-Dist: pandera[io] (>=0.23.1,<0.24.0) ; extra == "validate"
Requires-Dist: pyarrow (>=16.1.0,<17.0.0)
Requires-Dist: ydata-profiling (>=4.9.0,<5.0.0) ; extra == "profile"
Project-URL: Documentation, https://elphick.github.io/omfpandas
Project-URL: Repository, https://github.com/elphick/omfpandas
